<?xml version="1.0" encoding="UTF-8" ?>
<!DOCTYPE mapper PUBLIC "-//mybatis.org//DTD Mapper 3.0//EN" "http://mybatis.org/dtd/mybatis-3-mapper.dtd" >
<mapper namespace="com.rrh.mapper.user.TbUsersBankCardMapper" >
  <resultMap id="BaseResultMap" type="com.rrh.model.user.TbUsersBankCard" >
    <!--
      WARNING - @mbggenerated
      This element is automatically generated by MyBatis Generator, do not modify.
      This element was generated on Wed Nov 25 14:34:16 CST 2015.
    -->
    <id column="card_id" property="cardId" jdbcType="INTEGER" />
    <result column="card_num" property="cardNum" jdbcType="VARCHAR" />
    <result column="bank_id" property="bankId" jdbcType="INTEGER" />
    <result column="uset_id" property="usetId" jdbcType="INTEGER" />
    <result column="true_name" property="trueName" jdbcType="VARCHAR" />
  </resultMap>
  <delete id="deleteByPrimaryKey" parameterType="java.lang.Integer" >
    <!--
      WARNING - @mbggenerated
      This element is automatically generated by MyBatis Generator, do not modify.
      This element was generated on Wed Nov 25 14:34:16 CST 2015.
    -->
    delete from tb_users_bank_card
    where card_id = #{cardId,jdbcType=INTEGER}
  </delete>
  <insert id="insert" parameterType="com.rrh.model.user.TbUsersBankCard" >
    <!--
      WARNING - @mbggenerated
      This element is automatically generated by MyBatis Generator, do not modify.
      This element was generated on Wed Nov 25 14:34:16 CST 2015.
    -->
    insert into tb_users_bank_card (card_id, card_num, bank_id, 
      uset_id, true_name)
    values (#{cardId,jdbcType=INTEGER}, #{cardNum,jdbcType=VARCHAR}, #{bankId,jdbcType=INTEGER}, 
      #{usetId,jdbcType=INTEGER}, #{trueName,jdbcType=VARCHAR})
  </insert>
  <update id="updateByPrimaryKey" parameterType="com.rrh.model.user.TbUsersBankCard" >
    <!--
      WARNING - @mbggenerated
      This element is automatically generated by MyBatis Generator, do not modify.
      This element was generated on Wed Nov 25 14:34:16 CST 2015.
    -->
    update tb_users_bank_card
    set card_num = #{cardNum,jdbcType=VARCHAR},
      bank_id = #{bankId,jdbcType=INTEGER},
      uset_id = #{usetId,jdbcType=INTEGER},
      true_name = #{trueName,jdbcType=VARCHAR}
    where card_id = #{cardId,jdbcType=INTEGER}
  </update>
  <select id="selectByPrimaryKey" resultMap="BaseResultMap" parameterType="java.lang.Integer" >
    <!--
      WARNING - @mbggenerated
      This element is automatically generated by MyBatis Generator, do not modify.
      This element was generated on Wed Nov 25 14:34:16 CST 2015.
    -->
    select card_id, card_num, bank_id, uset_id, true_name
    from tb_users_bank_card
    where card_id = #{cardId,jdbcType=INTEGER}
  </select>
  <select id="selectAll" resultMap="BaseResultMap" >
    <!--
      WARNING - @mbggenerated
      This element is automatically generated by MyBatis Generator, do not modify.
      This element was generated on Wed Nov 25 14:34:16 CST 2015.
    -->
    select card_id, card_num, bank_id, uset_id, true_name
    from tb_users_bank_card
  </select>
</mapper>